nxva/__init__.py
nxva/logger.py
nxva/tools.py
nxva/vision.py
nxva/nxaxcl/__init__.py
nxva/nxaxcl/axcl_device.py
nxva/nxaxcl/axcl_infer.py
nxva/nxaxcl/axcl_inference_session.py
nxva/nxaxcl/axcl_model.py
nxva/nxaxcl/axcl_system.py
nxva/nxhailo/__init__.py
nxva/nxhailo/convert/__init__.py
nxva/nxhailo/convert/calib_transform.py
nxva/nxhailo/convert/hef_convert.py
nxva/nxhailo/convert/hef_convert_pipeline.py
nxva/nxhailo/convert/utils.py
nxva/nxhailo/inference/__init__.py
nxva/nxhailo/inference/feat_process.py
nxva/nxhailo/inference/inference.py
nxva/nxkp/__init__.py
nxva/nxkp/convert.py
nxva/nxkp/decode_head.py
nxva/nxkp/device.py
nxva/nxkp/inference.py
nxva/nxtrt/__init__.py
nxva/nxtrt/calibrator.py
nxva/nxtrt/convert.py
nxva/nxtrt/data_process.py
nxva/nxtrt/trt_inference.py
nxva/pose/__init__.py
nxva/pose/mmpose_builder.py
nxva/pose/mmpose_estimator.py
nxva/sort/__init__.py
nxva/sort/kalmanfilter.py
nxva/sort/nx_sort.py
nxva/sort/nx_track.py
nxva/sort/reid_model_factory.py
nxva/sort/reid_multibackend.py
nxva/sort/models/__init__.py
nxva/sort/models/irse.py
nxva/sort/models/osnet.py
nxva/sort/utils/KMmatcher.py
nxva/sort/utils/__init__.py
nxva/sort/utils/association.py
nxva/sort/utils/tools.py
nxva/streaming/__init__.py
nxva/streaming/ffmpeg_backend.py
nxva/streaming/multi_streaming.py
nxva/streaming/utils.py
nxva/toolbox/convert/extract_onnx.py
nxva/toolbox/result/__init__.py
nxva/toolbox/result/annotator.py
nxva/toolbox/result/plotting.py
nxva/toolbox/result/results.py
nxva/toolbox/val/__init__.py
nxva/toolbox/val/dataloader.py
nxva/toolbox/val/val_map.py
nxva/toolbox/val/val_speed.py
nxva/utilities/__init__.py
nxva/utilities/timer.py
nxva/v11/__init__.py
nxva/v11/classification.py
nxva/v11/detection.py
nxva/v11/pose_estimation.py
nxva/v5/__init__.py
nxva/v5/classification.py
nxva/v5/detection.py
nxva/v5/modelconvert.py
nxva/v5/pose_estimation.py
nxva/v5/yolov5/__init__.py
nxva/v5/yolov5/models/__init__.py
nxva/v5/yolov5/models/common.py
nxva-1.3.3.dist-info/licenses/LICENSE
nxva-1.3.3.dist-info/METADATA
nxva-1.3.3.dist-info/WHEEL
nxva-1.3.3.dist-info/top_level.txt
nxva-1.3.3.dist-info/RECORD
