Metadata-Version: 2.4
Name: nxva
Version: 1.3.3
Summary: tools for video analysis
Author-email: William Wu <science.william@gmail.com>
Maintainer-email: William Wu <science.william@gmail.com>
License: MIT
Project-URL: Homepage, https://github.com/nexuni/nxva.git
Project-URL: Documentation, https://github.com/nexuni/nxva#readme
Project-URL: Repository, https://github.com/nexuni/nxva.git
Project-URL: Bug Tracker, https://github.com/nexuni/nxva/issues
Project-URL: Changelog, https://github.com/nexuni/nxva/releases
Classifier: Development Status :: 3 - Alpha
Classifier: Intended Audience :: Developers
Classifier: License :: OSI Approved :: MIT License
Classifier: Operating System :: OS Independent
Classifier: Programming Language :: Python :: 3
Classifier: Programming Language :: Python :: 3.6
Classifier: Programming Language :: Python :: 3.7
Classifier: Programming Language :: Python :: 3.8
Classifier: Programming Language :: Python :: 3.9
Classifier: Programming Language :: Python :: 3.10
Classifier: Programming Language :: Python :: 3.11
Requires-Python: >=3.6
License-File: LICENSE
Dynamic: license-file
